ffprobe/__init__.py
ffprobe/exceptions.py
ffprobe/ffprobe.py
ffprobe_python-1.0.3.dist-info/LICENSE.txt
ffprobe_python-1.0.3.dist-info/METADATA
ffprobe_python-1.0.3.dist-info/WHEEL
ffprobe_python-1.0.3.dist-info/top_level.txt
ffprobe_python-1.0.3.dist-info/RECORD
