Metadata-Version: 2.1
Name: ffprobe-python
Version: 1.0.3
Summary: 
Home-page: https://github.com/gbstack/ffprobe-python
Author: Simon Hargreaves
Author-email: simon@simon-hargreaves.com
Maintainer: Mark Ma
Maintainer-email: 519329064@qq.com
License: UNKNOWN
Keywords: ffmpeg,ffprobe,mpeg,mp4
Platform: UNKNOWN
Classifier: Development Status :: 4 - Beta
Classifier: Environment :: Console
Classifier: Intended Audience :: Developers
Classifier: License :: OSI Approved :: MIT License
Classifier: Operating System :: MacOS :: MacOS X
Classifier: Operating System :: Microsoft :: Windows
Classifier: Operating System :: POSIX
Classifier: Programming Language :: Python
Classifier: Programming Language :: Python :: 2.7
Classifier: Programming Language :: Python :: 3.5
Classifier: Programming Language :: Python :: Implementation :: CPython
Classifier: Natural Language :: English
Classifier: Topic :: Multimedia :: Video
Classifier: Topic :: Software Development :: Libraries
